fpga/project/define.v

`define DELAY_SPI  				0
`define DELAY_STOP  				200

`define SPI_WIDHT  				8
`define MOUNT_BIT  				16
`define DATA_READ_RAZR  		16

`define LENTH_BUFER 			1025

`define CONTROL_REG_MAX       16

//FSMC parameter

`define FSMC_WIDTH  				16
`define RESET_WAIT				25

/*command FSMC*/

`define CMD_READ_1  				0
`define CMD_READ_2  				48

`define CMD_READ_ID					144

`define CMD_WRITE_1  				128
`define CMD_WRITE_2  				16


`define CMD_RESET					255  
`define CMD_READ_STATUS					112

fpga/project/memory.v
`include "define.v"

module memory(
	input wire CLK,
	input wire RESET,
	input wire READ_WRITE, //1- READ ; 0 -WRITE
	input wire [`FSMC_WIDTH-1:0] IN_DATA,
	output [`FSMC_WIDTH-1:0] OUT_DATA,
	input [15 : 0] 				COLUMN_ADDR,
	input [15 : 0] 					ROW_ADDR
);

reg [`FSMC_WIDTH-1:0] bufer[`LENTH_BUFER-1:0];
reg [`FSMC_WIDTH-1:0] out=16'b0000_0000_0000_0000;

wire [11:0]read_addr;
assign read_addr=COLUMN_ADDR[11:0];
always @(posedge CLK )
begin
   
		
        if (READ_WRITE==1)
		    out<=bufer[COLUMN_ADDR];
		  
        else
			bufer[read_addr]<=IN_DATA;
		  
       
	
end

assign OUT_DATA=out;
endmodule

fpga/project/fsmc.v
`include "define.v"

module fsmc(
input wire CLK,
input wire CLE,
input wire ALE,
input wire NRE,
input wire NCE,
input wire NWE,

output NWAIT,
output RESET_FSMC,

inout   [`FSMC_WIDTH-1:0] BIDIR,
input wire[`FSMC_WIDTH-1:0] IN_DATA,
output[`FSMC_WIDTH-1:0] OUT_DATA,

output [15 : 0] 				COLUMN_ADDR,
output [15 : 0] 					ROW_ADDR,
output READ_WRITE
//input wire STOP_BUFER
);

wire [7 : 0] in_bus;
wire [`FSMC_WIDTH-1:0]bus_data_com;
wire [`FSMC_WIDTH-1 : 0 ] DIn;
wire [`FSMC_WIDTH-1 : 0 ] wire_out;
assign DIn = BIDIR[`FSMC_WIDTH-1:0];
assign in_bus = BIDIR[7:0];


reg 								 reset_fsmc=1'b0;
reg							    read=1'b0;
reg [15 : 0] 					 column_addr=16'b0;
reg [15 : 0] 					 row_addr;
reg [7:0] 						 command;
reg [`FSMC_WIDTH-1:0]		 in_byte;

reg [`DATA_READ_RAZR-1:0]	 read_byte_cnt=16'b0;
reg [`FSMC_WIDTH-1:0]		 bus_out_bufer;	

reg [7:0]					status=8'b0000_0000;
reg [`FSMC_WIDTH-1:0]		 reg_for_write_to_memory=16'b0;	


`define STATE_IDLE  			0
`define STATE_WAIT_ROW  		1
`define STATE_WAIT_COLUMN  		2
`define STATE_READ_MEMORY   	3
`define STATE_WAIT_READ_MEMORY 	4
`define STATE_WRITE_MEMORY  	5
`define STATE_WAIT_WRITE_MEMORY 6

`define STATE_READ_ID   10
`define STATE_READ_STATUS   11

reg [7:0] avtomat=8'b0000_0000;

assign OUT_DATA = (avtomat==`STATE_WRITE_MEMORY) ? reg_for_write_to_memory: 16'b0000_0000_0000_0000;



assign COLUMN_ADDR = (avtomat==`STATE_READ_MEMORY) ? read_byte_cnt :column_addr;
assign BIDIR = (read==1'b1) ? wire_out : 16'bzzzz_zzzz_zzzz_zzzz;

assign RESET_FSMC = reset_fsmc;
assign NWAIT = 1'b0;


assign READ_WRITE= (avtomat==`STATE_WRITE_MEMORY) ? 1'b0 : 1'b1;



assign wire_out =(command==`CMD_READ_2) ? IN_DATA : bus_out_bufer;


initial
begin
	bus_out_bufer	=16'b0000_0000_0000_0000;
	read           =1'b0;
	command			=8'b0000_0000;
	column_addr		=16'b0000_0000_0000_0000;
	row_addr		=16'b0000_0000_0000_0000;
	in_byte			=8'b0000_0000;
	
end




always@ (negedge NRE or negedge ALE)
begin
	if (ALE==0)
	begin
		 read_byte_cnt<=column_addr;
	end
	else
	begin
		case(command)
			`CMD_READ_2:
			begin
			
				read_byte_cnt<=read_byte_cnt+1'b1;					
			end		
			`CMD_READ_STATUS:
			begin
				bus_out_bufer[15:8]<=8'b0000_0000;
				bus_out_bufer[7:0]<=status;
			end
			`CMD_READ_ID:
			begin
				bus_out_bufer[15:8]<=8'b0000_0000;
				bus_out_bufer[7:0]<=8'b0000_0000;
				
			end
			default:begin
			end
		endcase	
	end
end


always @(posedge NCE or negedge NRE)
begin
	if (NCE)
	begin
		read <= 1'b0;
	end
	else
	begin
		read <= 1'b1;

	end
end	

/*Latches 8 bit address on rising edge of WE#
Latches data on rising edge of WE#
*/

//assign COLUMN_ADDR = column_addr;
assign ROW_ADDR = row_addr;


always @ (posedge NWE or posedge NCE )
begin
	if (NCE)
	begin
		reset_fsmc<=1'b0;
		avtomat<=`STATE_IDLE;
	
	end
	else if (NWE)
	begin

		if ( ALE && ~NCE && ~CLE && NRE) //receive address
		begin	
			case (avtomat)
				`STATE_WAIT_COLUMN:
				begin
					if (command==`CMD_READ_1)
						column_addr<=DIn+1'b1 ;				
					else	
						column_addr<=DIn;				
					avtomat<=`STATE_WAIT_ROW;
				end
				`STATE_WAIT_ROW:
				begin
					row_addr<=DIn;	
					if (command==`CMD_WRITE_1)
					
						avtomat<=`STATE_WRITE_MEMORY;
					else
						avtomat<=`STATE_IDLE;
				end
				default:
				begin
				end
			endcase
			
		end
		if ( ~ALE  && ~NCE && ~CLE && NRE) //write byte
		begin

			if (command==`CMD_WRITE_1)
			begin
				reg_for_write_to_memory<=DIn;
				column_addr<=column_addr+1'b1;
			end
			
		end	
		if ( ~ALE && ~NCE && CLE && NRE)  //receive command
		begin	
			command <= in_bus[7:0];
			case(in_bus[7:0])
				
				`CMD_READ_1:
				begin
					column_addr		<=16'b0000_0000_0000_0000;
					row_addr		<=16'b0000_0000_0000_0000;
					avtomat<=`STATE_WAIT_ROW;
				end
				`CMD_READ_2:
				begin
				
					avtomat<=`STATE_READ_MEMORY;
				end	
				`CMD_WRITE_1:
				begin
					column_addr		<=16'b0000_0000_0000_0000;
					row_addr		<=16'b0000_0000_0000_0000;
					avtomat<=`STATE_WAIT_ROW;
				end
				`CMD_WRITE_2:
				begin
					
					avtomat<=`STATE_IDLE;
				end
				`CMD_RESET:reset_fsmc<=1'b1;
				`CMD_READ_STATUS:avtomat<=`STATE_READ_STATUS;
				
				default:begin
				end
			endcase	
		end	
	end
	else
	begin
	
	end
end

endmodule

fpga/project/project_fsmc.v
`include "define.v"

module project_fsmc(
input wire clk,
input wire cle,
input wire ale,
input wire nre,
input wire nce,
input wire nwe,

output nwait,
inout   [`FSMC_WIDTH-1:0] bidir

);


wire read_write;
wire reset;
wire [`FSMC_WIDTH-1:0]row_addr;
wire [`FSMC_WIDTH-1:0]column_addr;
wire [`FSMC_WIDTH-1:0]data_fsmc_to_memory;
wire [`FSMC_WIDTH-1:0]data_memory_to_fsmc;

fsmc fsmc_inst(
.CLK(clk),
.CLE(cle),
.ALE(ale),
.NRE(nre),
.NCE(nce),
.NWE(nwe),
.NWAIT(nwait),
.RESET_FSMC(reset),
.BIDIR(bidir),
.IN_DATA(data_memory_to_fsmc),
.OUT_DATA(data_fsmc_to_memory),
.COLUMN_ADDR (column_addr),
.ROW_ADDR(row_addr),
.READ_WRITE(read_write));

memory memory_inst(
.CLK(clk),
.RESET(reset),
.READ_WRITE(read_write),
.IN_DATA(data_fsmc_to_memory),
.OUT_DATA(data_memory_to_fsmc),
.COLUMN_ADDR(column_addr), 
.ROW_ADDR(row_addr));

endmodule

fpga/project/test_fsmc.v
module test_fsmc;

reg reset,clk,CLE,ALE,NRE,NCE,NWE;
input wire NWAIT;
inout   [`FSMC_WIDTH-1:0] BIDIR;
wire [`FSMC_WIDTH-1:0]  in_data;
reg [`FSMC_WIDTH-1:0]  out_data;
reg [`FSMC_WIDTH-1:0]  status;
reg read_write; // 1 - write ; 0 - read
assign BIDIR = (read_write==1) ? out_data : 16'bzzzz_zzzz_zzzz_zzzz;
project_fsmc project_fsmc(clk,CLE,ALE,NRE,NCE,NWE,NWAIT,BIDIR);

assign in_data = BIDIR[`FSMC_WIDTH-1:0] ;
reg [`FSMC_WIDTH-1:0]  i;
always
	#2 clk =~clk;

initial
begin
	clk = 0;
	reset=0;
	CLE=0;
	NCE=1;
	NWE=1;
	ALE=0;
	NRE=1;
	
	out_data=16'b0000_0000_0000_0000;
	//write page
	read_write=0;
	//#20	write=0;
	#10 reset=1;
	#10 reset =0;
	#20;
	CLE=1;
	NCE=0;
	read_write=1;
	out_data=16'b0000_0000_1000_0000;
	#5;
	NWE=0;
	#5
	NWE=1;
	#5
	CLE=0;
	ALE=1;
	#5
	out_data=16'b0000_0000_0000_0000; //column
	#5;
	NWE=0;
	#5
	NWE=1;
	#5;
	out_data=16'b0000_0000_0000_0000; //row
	NWE=0;
	#5
	NWE=1;
	#5;
	ALE=0;
	read_write=0;
	#10;
	read_write=1;
	#5;
	for (i=0; i < 16; i=i+1)
	begin
		
		
		NWE=0;
		#5;
		NWE=1;
		#5;
		out_data=out_data+1;
	end 
	read_write=0;
	#10;
	CLE=1;
	read_write=1;
	out_data=16'b0000_0000_0001_0000;
	#5;
	NWE=0;
	#5;
	NWE=1;
	#5;
	CLE=0;
	read_write=0;
	#20;
	read_write=1;
	CLE=1;
	NWE=0;
	out_data=16'b0000_0000_0111_0000;
	#5;
	NWE=1;
	#5;
	read_write=0;
	#5;
	CLE=0;
	NRE=0;
	#5;
	NRE=1;
	#5;
	NCE=1;
	#5
	//read_page
	read_write=1;
	CLE=1;
	NCE=0;
	NWE=0;
	ALE=0;
	NRE=1;
	out_data[7:0]=16'b0000_0000_0000_0000;
	#2;
	CLE=0;
	#5;
	NWE=1;
	#5;
	NWE=0;
	ALE=1;
	out_data=16'b0000_0000_0000_0000; //column
	#5;
	NWE=1;
	#5;
	NWE=0;
	out_data=16'b0000_0000_0000_0000; //row
	#5;
	NWE=1;
	#3;
	ALE=0;
	#2;
	CLE=1;
	NWE=0;
	out_data=16'b0000_0000_0011_0000;
	#5;
	NWE=1;
	#2;
	CLE=0;
	#20;
	read_write=0;
	for (i=0; i < 16; i=i+1)
	begin
		NRE=0;
		#5;
		NRE=1;
		#5;
	end 
	#20;
	NCE=1;
end

initial
begin
	#800 $finish;
end

initial
begin
$dumpfile("out.vcd");
$dumpvars(0,test_fsmc);
end

endmodule

fpga/project/out.vcd
$date
	Fri Jul  3 00:03:38 2015
$end
$version
	Icarus Verilog
$end
$timescale
	1s
$end
$scope module test_fsmc $end
$var wire 16 ! BIDIR [15:0] $end
$var wire 1 " NWAIT $end
$var wire 16 # in_data [15:0] $end
$var reg 1 $ ALE $end
$var reg 1 % CLE $end
$var reg 1 & NCE $end
$var reg 1 ' NRE $end
$var reg 1 ( NWE $end
$var reg 1 ) clk $end
$var reg 16 * i [15:0] $end
$var reg 16 + out_data [15:0] $end
$var reg 1 , read_write $end
$var reg 1 - reset $end
$scope module project_fsmc $end
$var wire 1 . ale $end
$var wire 16 / bidir [15:0] $end
$var wire 1 0 cle $end
$var wire 1 1 clk $end
$var wire 16 2 column_addr [15:0] $end
$var wire 16 3 data_fsmc_to_memory [15:0] $end
$var wire 16 4 data_memory_to_fsmc [15:0] $end
$var wire 1 5 nce $end
$var wire 1 6 nre $end
$var wire 1 " nwait $end
$var wire 1 7 nwe $end
$var wire 1 8 read_write $end
$var wire 1 9 reset $end
$var wire 16 : row_addr [15:0] $end
$scope module fsmc_inst $end
$var wire 1 . ALE $end
$var wire 16 ; BIDIR [15:0] $end
$var wire 1 0 CLE $end
$var wire 1 1 CLK $end
$var wire 16 < COLUMN_ADDR [15:0] $end
$var wire 16 = DIn [15:0] $end
$var wire 16 > IN_DATA [15:0] $end
$var wire 1 5 NCE $end
$var wire 1 6 NRE $end
$var wire 1 " NWAIT $end
$var wire 1 7 NWE $end
$var wire 16 ? OUT_DATA [15:0] $end
$var wire 1 8 READ_WRITE $end
$var wire 1 9 RESET_FSMC $end
$var wire 16 @ ROW_ADDR [15:0] $end
$var wire 8 A in_bus [7:0] $end
$var wire 16 B wire_out [15:0] $end
$var reg 8 C avtomat [7:0] $end
$var reg 16 D bus_out_bufer [15:0] $end
$var reg 16 E column_addr [15:0] $end
$var reg 8 F command [7:0] $end
$var reg 16 G in_byte [15:0] $end
$var reg 1 H read $end
$var reg 16 I read_byte_cnt [15:0] $end
$var reg 16 J reg_for_write_to_memory [15:0] $end
$var reg 1 K reset_fsmc $end
$var reg 16 L row_addr [15:0] $end
$var reg 8 M status [7:0] $end
$upscope $end
$scope module memory_inst $end
$var wire 1 1 CLK $end
$var wire 16 N COLUMN_ADDR [15:0] $end
$var wire 16 O IN_DATA [15:0] $end
$var wire 16 P OUT_DATA [15:0] $end
$var wire 1 8 READ_WRITE $end
$var wire 1 9 RESET $end
$var wire 16 Q ROW_ADDR [15:0] $end
$var wire 12 R read_addr [11:0] $end
$var reg 16 S out [15:0] $end
$upscope $end
$upscope $end
$upscope $end
$enddefinitions $end
#0
$dumpvars
bx S
b0 R
b0 Q
bx P
b0 O
b0 N
b0 M
b0 L
0K
b0 J
b0 I
0H
b0 G
b0 F
b0 E
b0 D
b0 C
b0 B
bz A
b0 @
b0 ?
bx >
bz =
b0 <
bz ;
b0 :
09
18
17
16
15
bx 4
b0 3
b0 2
01
00
bz /
0.
0-
0,
b0 +
bx *
0)
1(
1'
1&
0%
0$
bz #
0"
bz !
$end
#2
1)
11
#4
0)
01
#6
1)
11
#8
0)
01
#10
1)
11
1-
#12
0)
01
#14
1)
11
#16
0)
01
#18
1)
11
#20
0)
01
0-
#22
1)
11
#24
0)
01
#26
1)
11
#28
0)
01
#30
1)
11
#32
0)
01
#34
1)
11
#36
0)
01
#38
1)
11
#40
b10000000 A
b10000000 #
b10000000 !
b10000000 /
b10000000 ;
b10000000 =
0)
01
b10000000 +
1,
0&
05
1%
10
#42
1)
11
#44
0)
01
#45
0(
07
#46
1)
11
#48
0)
01
#50
b1 C
b10000000 F
1)
11
1(
17
#52
0)
01
#54
1)
11
#55
1$
1.
0%
00
#56
0)
01
#58
1)
11
#60
b0 A
b0 #
b0 !
b0 /
b0 ;
b0 =
0)
01
b0 +
#62
1)
11
#64
0)
01
#65
0(
07
#66
1)
11
#68
0)
01
#70
08
b101 C
1)
11
1(
17
#72
0)
01
#74
1)
11
#75
0(
07
#76
0)
01
#78
1)
11
#80
0)
01
1(
17
#82
1)
11
#84
0)
01
#85
bz A
bz #
bz !
bz /
bz ;
bz =
0,
0$
0.
#86
1)
11
#88
0)
01
#90
1)
11
#92
0)
01
#94
1)
11
#95
b0 A
b0 #
b0 !
b0 /
b0 ;
b0 =
1,
#96
0)
01
#98
1)
11
#100
0)
01
0(
07
b0 *
#102
1)
11
#104
0)
01
#105
b1 R
b1 2
b1 <
b1 N
b1 E
1(
17
#106
1)
11
#108
0)
01
#110
b1 A
b1 #
b1 !
b1 /
b1 ;
b1 =
1)
11
0(
07
b1 *
b1 +
#112
0)
01
#114
1)
11
#115
b1 3
b1 ?
b1 O
b1 J
b10 R
b10 2
b10 <
b10 N
b10 E
1(
17
#116
0)
01
#118
1)
11
#120
b10 A
b10 #
b10 !
b10 /
b10 ;
b10 =
0)
01
0(
07
b10 *
b10 +
#122
1)
11
#124
0)
01
#125
b10 3
b10 ?
b10 O
b10 J
b11 R
b11 2
b11 <
b11 N
b11 E
1(
17
#126
1)
11
#128
0)
01
#130
b11 A
b11 #
b11 !
b11 /
b11 ;
b11 =
1)
11
0(
07
b11 *
b11 +
#132
0)
01
#134
1)
11
#135
b11 3
b11 ?
b11 O
b11 J
b100 R
b100 2
b100 <
b100 N
b100 E
1(
17
#136
0)
01
#138
1)
11
#140
b100 A
b100 #
b100 !
b100 /
b100 ;
b100 =
0)
01
0(
07
b100 *
b100 +
#142
1)
11
#144
0)
01
#145
b100 3
b100 ?
b100 O
b100 J
b101 R
b101 2
b101 <
b101 N
b101 E
1(
17
#146
1)
11
#148
0)
01
#150
b101 A
b101 #
b101 !
b101 /
b101 ;
b101 =
1)
11
0(
07
b101 *
b101 +
#152
0)
01
#154
1)
11
#155
b101 3
b101 ?
b101 O
b101 J
b110 R
b110 2
b110 <
b110 N
b110 E
1(
17
#156
0)
01
#158
1)
11
#160
b110 A
b110 #
b110 !
b110 /
b110 ;
b110 =
0)
01
0(
07
b110 *
b110 +
#162
1)
11
#164
0)
01
#165
b110 3
b110 ?
b110 O
b110 J
b111 R
b111 2
b111 <
b111 N
b111 E
1(
17
#166
1)
11
#168
0)
01
#170
b111 A
b111 #
b111 !
b111 /
b111 ;
b111 =
1)
11
0(
07
b111 *
b111 +
#172
0)
01
#174
1)
11
#175
b111 3
b111 ?
b111 O
b111 J
b1000 R
b1000 2
b1000 <
b1000 N
b1000 E
1(
17
#176
0)
01
#178
1)
11
#180
b1000 A
b1000 #
b1000 !
b1000 /
b1000 ;
b1000 =
0)
01
0(
07
b1000 *
b1000 +
#182
1)
11
#184
0)
01
#185
b1000 3
b1000 ?
b1000 O
b1000 J
b1001 R
b1001 2
b1001 <
b1001 N
b1001 E
1(
17
#186
1)
11
#188
0)
01
#190
b1001 A
b1001 #
b1001 !
b1001 /
b1001 ;
b1001 =
1)
11
0(
07
b1001 *
b1001 +
#192
0)
01
#194
1)
11
#195
b1001 3
b1001 ?
b1001 O
b1001 J
b1010 R
b1010 2
b1010 <
b1010 N
b1010 E
1(
17
#196
0)
01
#198
1)
11
#200
b1010 A
b1010 #
b1010 !
b1010 /
b1010 ;
b1010 =
0)
01
0(
07
b1010 *
b1010 +
#202
1)
11
#204
0)
01
#205
b1010 3
b1010 ?
b1010 O
b1010 J
b1011 R
b1011 2
b1011 <
b1011 N
b1011 E
1(
17
#206
1)
11
#208
0)
01
#210
b1011 A
b1011 #
b1011 !
b1011 /
b1011 ;
b1011 =
1)
11
0(
07
b1011 *
b1011 +
#212
0)
01
#214
1)
11
#215
b1011 3
b1011 ?
b1011 O
b1011 J
b1100 R
b1100 2
b1100 <
b1100 N
b1100 E
1(
17
#216
0)
01
#218
1)
11
#220
b1100 A
b1100 #
b1100 !
b1100 /
b1100 ;
b1100 =
0)
01
0(
07
b1100 *
b1100 +
#222
1)
11
#224
0)
01
#225
b1100 3
b1100 ?
b1100 O
b1100 J
b1101 R
b1101 2
b1101 <
b1101 N
b1101 E
1(
17
#226
1)
11
#228
0)
01
#230
b1101 A
b1101 #
b1101 !
b1101 /
b1101 ;
b1101 =
1)
11
0(
07
b1101 *
b1101 +
#232
0)
01
#234
1)
11
#235
b1101 3
b1101 ?
b1101 O
b1101 J
b1110 R
b1110 2
b1110 <
b1110 N
b1110 E
1(
17
#236
0)
01
#238
1)
11
#240
b1110 A
b1110 #
b1110 !
b1110 /
b1110 ;
b1110 =
0)
01
0(
07
b1110 *
b1110 +
#242
1)
11
#244
0)
01
#245
b1110 3
b1110 ?
b1110 O
b1110 J
b1111 R
b1111 2
b1111 <
b1111 N
b1111 E
1(
17
#246
1)
11
#248
0)
01
#250
b1111 A
b1111 #
b1111 !
b1111 /
b1111 ;
b1111 =
1)
11
0(
07
b1111 *
b1111 +
#252
0)
01
#254
1)
11
#255
b1111 3
b1111 ?
b1111 O
b1111 J
b10000 R
b10000 2
b10000 <
b10000 N
b10000 E
1(
17
#256
0)
01
#258
1)
11
#260
bz A
bz #
bz !
bz /
bz ;
bz =
0)
01
0,
b10000 *
b10000 +
#262
1)
11
#264
0)
01
#266
1)
11
#268
0)
01
#270
b10000 A
b10000 #
b10000 !
b10000 /
b10000 ;
b10000 =
1)
11
1,
1%
10
#272
0)
01
#274
1)
11
#275
0(
07
#276
0)
01
#278
1)
11
#280
b0 3
b0 ?
b0 O
18
b0 C
b10000 F
0)
01
1(
17
#282
b1111 S
b1111 4
b1111 >
b1111 P
1)
11
#284
0)
01
#285
bz A
bz #
bz !
bz /
bz ;
bz =
0,
0%
00
#286
1)
11
#288
0)
01
#290
1)
11
#292
0)
01
#294
1)
11
#296
0)
01
#298
1)
11
#300
0)
01
#302
1)
11
#304
0)
01
#305
b1110000 A
b1110000 #
b1110000 !
b1110000 /
b1110000 ;
b1110000 =
b1110000 +
0(
07
1%
10
1,
#306
1)
11
#308
0)
01
#310
b1011 C
b1110000 F
1)
11
1(
17
#312
0)
01
#314
1)
11
#315
bz A
bz #
bz !
bz /
bz ;
bz =
0,
#316
0)
01
#318
1)
11
#320
b0 A
b0 #
b0 !
b0 /
b0 ;
b0 =
1H
b0 D
0)
01
0'
06
0%
00
#322
1)
11
#324
0)
01
#325
1'
16
#326
1)
11
#328
0)
01
#330
bz A
bz #
bz !
bz /
bz ;
bz =
b0 C
0H
1)
11
1&
15
#332
0)
01
#334
1)
11
#335
b0 A
b0 #
b0 !
b0 /
b0 ;
b0 =
b0 +
0(
07
0&
05
1%
10
1,
#336
0)
01
#337
0%
00
#338
1)
11
#340
0)
01
#342
1)
11
1(
17
#344
0)
01
#346
1)
11
#347
1$
1.
0(
07
#348
0)
01
#350
1)
11
#352
0)
01
1(
17
#354
1)
11
#356
0)
01
#357
0(
07
#358
1)
11
#360
0)
01
#362
1)
11
1(
17
#364
0)
01
#365
b0 D
0$
0.
#366
1)
11
#367
b110000 A
b110000 #
b110000 !
b110000 /
b110000 ;
b110000 =
b110000 +
0(
07
1%
10
#368
0)
01
#370
1)
11
#372
b0 R
b0 2
b0 <
b0 N
b1111 B
b11 C
b110000 F
0)
01
1(
17
#374
b0 B
b0 S
b0 4
b0 >
b0 P
1)
11
0%
00
#376
0)
01
#378
1)
11
#380
0)
01
#382
1)
11
#384
0)
01
#386
1)
11
#388
0)
01
#390
1)
11
#392
0)
01
#394
b1 R
b1 2
b1 <
b1 N
1H
b1 I
b0 A
b0 #
b0 !
b0 /
b0 ;
b0 =
1)
11
0'
06
b0 *
0,
#396
0)
01
#398
1)
11
#399
1'
16
#400
0)
01
#402
1)
11
#404
b10 R
b10 2
b10 <
b10 N
b10 I
0)
01
0'
06
b1 *
#406
b1 A
b1 #
b1 !
b1 /
b1 ;
b1 =
b1 B
b1 S
b1 4
b1 >
b1 P
1)
11
#408
0)
01
#409
1'
16
#410
1)
11
#412
0)
01
#414
b11 R
b11 2
b11 <
b11 N
b11 I
1)
11
0'
06
b10 *
#416
b10 A
b10 #
b10 !
b10 /
b10 ;
b10 =
b10 B
b10 S
b10 4
b10 >
b10 P
0)
01
#418
1)
11
#419
1'
16
#420
0)
01
#422
1)
11
#424
b100 R
b100 2
b100 <
b100 N
b100 I
0)
01
0'
06
b11 *
#426
b11 A
b11 #
b11 !
b11 /
b11 ;
b11 =
b11 B
b11 S
b11 4
b11 >
b11 P
1)
11
#428
0)
01
#429
1'
16
#430
1)
11
#432
0)
01
#434
b101 R
b101 2
b101 <
b101 N
b101 I
1)
11
0'
06
b100 *
#436
b100 A
b100 #
b100 !
b100 /
b100 ;
b100 =
b100 B
b100 S
b100 4
b100 >
b100 P
0)
01
#438
1)
11
#439
1'
16
#440
0)
01
#442
1)
11
#444
b110 R
b110 2
b110 <
b110 N
b110 I
0)
01
0'
06
b101 *
#446
b101 A
b101 #
b101 !
b101 /
b101 ;
b101 =
b101 B
b101 S
b101 4
b101 >
b101 P
1)
11
#448
0)
01
#449
1'
16
#450
1)
11
#452
0)
01
#454
b111 R
b111 2
b111 <
b111 N
b111 I
1)
11
0'
06
b110 *
#456
b110 A
b110 #
b110 !
b110 /
b110 ;
b110 =
b110 B
b110 S
b110 4
b110 >
b110 P
0)
01
#458
1)
11
#459
1'
16
#460
0)
01
#462
1)
11
#464
b1000 R
b1000 2
b1000 <
b1000 N
b1000 I
0)
01
0'
06
b111 *
#466
b111 A
b111 #
b111 !
b111 /
b111 ;
b111 =
b111 B
b111 S
b111 4
b111 >
b111 P
1)
11
#468
0)
01
#469
1'
16
#470
1)
11
#472
0)
01
#474
b1001 R
b1001 2
b1001 <
b1001 N
b1001 I
1)
11
0'
06
b1000 *
#476
b1000 A
b1000 #
b1000 !
b1000 /
b1000 ;
b1000 =
b1000 B
b1000 S
b1000 4
b1000 >
b1000 P
0)
01
#478
1)
11
#479
1'
16
#480
0)
01
#482
1)
11
#484
b1010 R
b1010 2
b1010 <
b1010 N
b1010 I
0)
01
0'
06
b1001 *
#486
b1001 A
b1001 #
b1001 !
b1001 /
b1001 ;
b1001 =
b1001 B
b1001 S
b1001 4
b1001 >
b1001 P
1)
11
#488
0)
01
#489
1'
16
#490
1)
11
#492
0)
01
#494
b1011 R
b1011 2
b1011 <
b1011 N
b1011 I
1)
11
0'
06
b1010 *
#496
b1010 A
b1010 #
b1010 !
b1010 /
b1010 ;
b1010 =
b1010 B
b1010 S
b1010 4
b1010 >
b1010 P
0)
01
#498
1)
11
#499
1'
16
#500
0)
01
#502
1)
11
#504
b1100 R
b1100 2
b1100 <
b1100 N
b1100 I
0)
01
0'
06
b1011 *
#506
b1011 A
b1011 #
b1011 !
b1011 /
b1011 ;
b1011 =
b1011 B
b1011 S
b1011 4
b1011 >
b1011 P
1)
11
#508
0)
01
#509
1'
16
#510
1)
11
#512
0)
01
#514
b1101 R
b1101 2
b1101 <
b1101 N
b1101 I
1)
11
0'
06
b1100 *
#516
b1100 A
b1100 #
b1100 !
b1100 /
b1100 ;
b1100 =
b1100 B
b1100 S
b1100 4
b1100 >
b1100 P
0)
01
#518
1)
11
#519
1'
16
#520
0)
01
#522
1)
11
#524
b1110 R
b1110 2
b1110 <
b1110 N
b1110 I
0)
01
0'
06
b1101 *
#526
b1101 A
b1101 #
b1101 !
b1101 /
b1101 ;
b1101 =
b1101 B
b1101 S
b1101 4
b1101 >
b1101 P
1)
11
#528
0)
01
#529
1'
16
#530
1)
11
#532
0)
01
#534
b1111 R
b1111 2
b1111 <
b1111 N
b1111 I
1)
11
0'
06
b1110 *
#536
b1110 A
b1110 #
b1110 !
b1110 /
b1110 ;
b1110 =
b1110 B
b1110 S
b1110 4
b1110 >
b1110 P
0)
01
#538
1)
11
#539
1'
16
#540
0)
01
#542
1)
11
#544
b10000 R
b10000 2
b10000 <
b10000 N
b10000 I
0)
01
0'
06
b1111 *
#546
b1111 A
b1111 #
b1111 !
b1111 /
b1111 ;
b1111 =
b1111 B
b1111 S
b1111 4
b1111 >
b1111 P
1)
11
#548
0)
01
#549
1'
16
#550
1)
11
#552
0)
01
#554
1)
11
b10000 *
#556
0)
01
#558
1)
11
#560
0)
01
#562
1)
11
#564
0)
01
#566
1)
11
#568
0)
01
#570
1)
11
#572
0)
01
#574
bz A
bz #
bz !
bz /
bz ;
bz =
b0 C
0H
1)
11
1&
15
